creddit/__init__.py
creddit/__main__.py
creddit/config.py
creddit/py.typed
creddit/reddit.py
creddit/terminal.py
creddit-0.0.3.dist-info/licenses/LICENSE
creddit-0.0.3.dist-info/METADATA
creddit-0.0.3.dist-info/WHEEL
creddit-0.0.3.dist-info/top_level.txt
creddit-0.0.3.dist-info/RECORD
