Metadata-Version: 2.4
Name: creddit
Version: 0.0.3
Summary: An unofficial cli client for Reddit, aimed at people who regularly browse specific subreddits or topics instead of reading the homepage (r/all).
Author-email: Vishal Nandagopal <dev@vishalnandagopal.com>
License-Expression: MIT
Requires-Python: >=3.13
License-File: LICENSE
Requires-Dist: colorama>=0.4.6
Requires-Dist: python-dotenv>=1.1.0
Requires-Dist: requests>=2.32.3
Dynamic: license-file
